djust/__init__.py
djust/__main__.py
djust/_rust.cpython-312-x86_64-linux-gnu.so
djust/cli.py
djust/components/__init__.py
djust/components/base.py
djust/components/data/__init__.py
djust/components/data/pagination.py
djust/components/data/table.py
djust/components/dependencies.py
djust/components/forms/__init__.py
djust/components/forms/foreign_key.py
djust/components/layout/__init__.py
djust/components/layout/navbar.py
djust/components/layout/tabs.py
djust/components/registry.py
djust/components/ui/__init__.py
djust/components/ui/accordion_simple.py
djust/components/ui/alert.py
djust/components/ui/alert_simple.py
djust/components/ui/avatar_simple.py
djust/components/ui/badge.py
djust/components/ui/badge_simple.py
djust/components/ui/breadcrumb_simple.py
djust/components/ui/button.py
djust/components/ui/button_group_simple.py
djust/components/ui/button_simple.py
djust/components/ui/card.py
djust/components/ui/card_simple.py
djust/components/ui/checkbox_simple.py
djust/components/ui/divider_simple.py
djust/components/ui/dropdown.py
djust/components/ui/dropdown_simple.py
djust/components/ui/icon_simple.py
djust/components/ui/input_simple.py
djust/components/ui/list_group_simple.py
djust/components/ui/modal.py
djust/components/ui/modal_simple.py
djust/components/ui/navbar_simple.py
djust/components/ui/offcanvas_simple.py
djust/components/ui/pagination_simple.py
djust/components/ui/progress.py
djust/components/ui/progress_simple.py
djust/components/ui/radio_simple.py
djust/components/ui/range_simple.py
djust/components/ui/select_simple.py
djust/components/ui/spinner.py
djust/components/ui/spinner_simple.py
djust/components/ui/switch_simple.py
djust/components/ui/table_simple.py
djust/components/ui/tabs_simple.py
djust/components/ui/textarea_simple.py
djust/components/ui/toast_simple.py
djust/components/ui/tooltip_simple.py
djust/config.py
djust/decorators.py
djust/dev_server.py
djust/djust2_logo.pxd
djust/djust3_logo.pxd
djust/drafts.py
djust/forms.py
djust-0.2.1.dist-info/METADATA
djust-0.2.1.dist-info/WHEEL
djust-0.2.1.dist-info/entry_points.txt
djust-0.2.1.dist-info/licenses/LICENSE
djust-0.2.1.dist-info/RECORD
