Metadata-Version: 2.4
Name: djust
Version: 0.2.1
Classifier: Development Status :: 3 - Alpha
Classifier: Framework :: Django
Classifier: Framework :: Django :: 3.2
Classifier: Framework :: Django :: 4.0
Classifier: Framework :: Django :: 4.1
Classifier: Framework :: Django :: 4.2
Classifier: Framework :: Django :: 5.0
Classifier: Intended Audience :: Developers
Classifier: License :: OSI Approved :: MIT License
Classifier: Programming Language :: Python :: 3
Classifier: Programming Language :: Python :: 3.8
Classifier: Programming Language :: Python :: 3.9
Classifier: Programming Language :: Python :: 3.10
Classifier: Programming Language :: Python :: 3.11
Classifier: Programming Language :: Python :: 3.12
Classifier: Programming Language :: Rust
Classifier: Topic :: Internet :: WWW/HTTP
Classifier: Topic :: Software Development :: Libraries :: Python Modules
Requires-Dist: django>=3.2
Requires-Dist: channels[daphne]>=4.0.0
Requires-Dist: msgpack>=1.0.0
Requires-Dist: zstandard>=0.22.0 ; extra == 'compression'
Requires-Dist: maturin>=1.0,<2.0 ; extra == 'dev'
Requires-Dist: pytest>=7.0 ; extra == 'dev'
Requires-Dist: pytest-django>=4.5 ; extra == 'dev'
Requires-Dist: pytest-asyncio>=0.21 ; extra == 'dev'
Requires-Dist: pytest-xdist>=3.0 ; extra == 'dev'
Requires-Dist: pytest-benchmark>=4.0.0 ; extra == 'dev'
Requires-Dist: black>=23.0 ; extra == 'dev'
Requires-Dist: ruff>=0.1 ; extra == 'dev'
Requires-Dist: mypy>=1.0 ; extra == 'dev'
Requires-Dist: uvicorn[standard]>=0.30.0 ; extra == 'dev'
Requires-Dist: whitenoise>=6.0.0 ; extra == 'dev'
Requires-Dist: redis>=5.0.0 ; extra == 'dev'
Requires-Dist: watchdog>=3.0.0 ; extra == 'dev'
Requires-Dist: zstandard>=0.22.0 ; extra == 'dev'
Requires-Dist: orjson>=3.9.0 ; extra == 'dev'
Requires-Dist: orjson>=3.9.0 ; extra == 'performance'
Requires-Dist: zstandard>=0.22.0 ; extra == 'performance'
Requires-Dist: redis>=5.0.0 ; extra == 'redis'
Provides-Extra: compression
Provides-Extra: dev
Provides-Extra: performance
Provides-Extra: redis
License-File: LICENSE
Summary: Blazing fast reactive server-side rendering for Django, powered by Rust
Keywords: django,rust,reactive,server-side-rendering,websocket
Author: djust contributors
License: MIT
Requires-Python: >=3.8
Project-URL: Changelog, https://github.com/djust-org/djust/blob/main/CHANGELOG.md
Project-URL: Documentation, https://djust.org/quickstart/
Project-URL: Homepage, https://djust.org
Project-URL: Issues, https://github.com/djust-org/djust/issues
Project-URL: Repository, https://github.com/djust-org/djust
